sphinxcontrib/moderncmakedomain/__init__.py
sphinxcontrib/moderncmakedomain/cmake.py
sphinxcontrib/moderncmakedomain/colors.py
sphinxcontrib_moderncmakedomain-3.29.0.dist-info/METADATA
sphinxcontrib_moderncmakedomain-3.29.0.dist-info/WHEEL
sphinxcontrib_moderncmakedomain-3.29.0.dist-info/licenses/LICENSE
sphinxcontrib_moderncmakedomain-3.29.0.dist-info/RECORD
