Metadata-Version: 2.3
Name: sphinxcontrib-moderncmakedomain
Version: 3.29.0
Summary: Sphinx Domain for Modern CMake
Project-URL: Homepage, https://github.com/scikit-build/moderncmakedomain
Author: Kitware
License-File: LICENSE
Keywords: cmake,documentation,kitware,sphinx,sphinxcontrib
Classifier: Environment :: Console
Classifier: Environment :: Web Environment
Classifier: Framework :: Sphinx :: Domain
Classifier: Framework :: Sphinx :: Extension
Classifier: Intended Audience :: Developers
Classifier: License :: OSI Approved :: BSD License
Classifier: Operating System :: OS Independent
Classifier: Programming Language :: Python :: 3 :: Only
Classifier: Programming Language :: Python :: 3.7
Classifier: Programming Language :: Python :: 3.8
Classifier: Programming Language :: Python :: 3.9
Classifier: Programming Language :: Python :: 3.10
Classifier: Programming Language :: Python :: 3.11
Classifier: Programming Language :: Python :: 3.12
Classifier: Programming Language :: Python :: 3.13
Classifier: Topic :: Documentation
Classifier: Topic :: Utilities
Requires-Python: >=3.7
Requires-Dist: sphinx>=2
Provides-Extra: test
Requires-Dist: defusedxml; extra == 'test'
Requires-Dist: pytest; extra == 'test'
